examples/__init__.py
examples/concertbot/__init__.py
examples/concertbot/actions.py
examples/knowledgebasebot/__init__.py
examples/knowledgebasebot/actions.py
examples/nlg_server/__init__.py
examples/nlg_server/nlg_server.py
examples/reminderbot/__init__.py
examples/reminderbot/actions.py
examples/restaurantbot/__init__.py
examples/restaurantbot/actions.py
examples/restaurantbot/policy.py
examples/restaurantbot/run.py
rasa/__init__.py
rasa/__main__.py
rasa/constants.py
rasa/data.py
rasa/exceptions.py
rasa/jupyter.py
rasa/model.py
rasa/run.py
rasa/server.py
rasa/test.py
rasa/train.py
rasa/validator.py
rasa/version.py
rasa/cli/__init__.py
rasa/cli/data.py
rasa/cli/default_config.yml
rasa/cli/export.py
rasa/cli/interactive.py
rasa/cli/run.py
rasa/cli/scaffold.py
rasa/cli/shell.py
rasa/cli/test.py
rasa/cli/train.py
rasa/cli/utils.py
rasa/cli/visualize.py
rasa/cli/x.py
rasa/cli/arguments/__init__.py
rasa/cli/arguments/data.py
rasa/cli/arguments/default_arguments.py
rasa/cli/arguments/export.py
rasa/cli/arguments/interactive.py
rasa/cli/arguments/run.py
rasa/cli/arguments/shell.py
rasa/cli/arguments/test.py
rasa/cli/arguments/train.py
rasa/cli/arguments/visualize.py
rasa/cli/arguments/x.py
rasa/cli/initial_project/__init__.py
rasa/cli/initial_project/actions.py
rasa/cli/initial_project/config.yml
rasa/cli/initial_project/credentials.yml
rasa/cli/initial_project/domain.yml
rasa/cli/initial_project/endpoints.yml
rasa/cli/initial_project/data/nlu.md
rasa/cli/initial_project/data/stories.md
rasa/core/__init__.py
rasa/core/agent.py
rasa/core/config.py
rasa/core/constants.py
rasa/core/conversation.py
rasa/core/domain.py
rasa/core/evaluate.py
rasa/core/exceptions.py
rasa/core/exporter.py
rasa/core/featurizers.py
rasa/core/interpreter.py
rasa/core/jobs.py
rasa/core/lock.py
rasa/core/lock_store.py
rasa/core/processor.py
rasa/core/registry.py
rasa/core/restore.py
rasa/core/run.py
rasa/core/slots.py
rasa/core/test.py
rasa/core/tracker_store.py
rasa/core/trackers.py
rasafou-1.7.49.dist-info/LICENSE.txt
rasafou-1.7.49.dist-info/METADATA
rasafou-1.7.49.dist-info/WHEEL
rasafou-1.7.49.dist-info/entry_points.txt
rasafou-1.7.49.dist-info/top_level.txt
rasafou-1.7.49.dist-info/RECORD
